{"trial_id": "09", "hyperparameters": {"space": [{"class_name": "Choice", "config": {"name": "lr", "default": 0.001, "conditions": [], "values": [0.001, 0.05, 0.01], "ordered": true}}, {"class_name": "Int", "config": {"name": "input_tnetconv", "default": null, "conditions": [], "min_value": 1, "max_value": 5, "step": 1, "sampling": "linear"}}, {"class_name": "Choice", "config": {"name": "input_tnetfilters_0", "default": 0, "conditions": [], "values": [0, 8, 16, 32, 64], "ordered": true}}, {"class_name": "Choice", "config": {"name": "input_tnetconv_dropout", "default": 0.0, "conditions": [], "values": [0.0, 0.1, 0.2], "ordered": true}}, {"class_name": "Int", "config": {"name": "input_tnetdense", "default": null, "conditions": [], "min_value": 1, "max_value": 5, "step": 1, "sampling": "linear"}}, {"class_name": "Choice", "config": {"name": "units0", "default": 0, "conditions": [], "values": [0, 8, 16, 32, 64], "ordered": true}}, {"class_name": "Choice", "config": {"name": "input_tnetdense_dropout", "default": 0.0, "conditions": [], "values": [0.0, 0.1, 0.2], "ordered": true}}, {"class_name": "Choice", "config": {"name": "encoder", "default": 0, "conditions": [], "values": [0, 8, 16, 32, 64], "ordered": true}}, {"class_name": "Int", "config": {"name": "feature_tnetconv", "default": null, "conditions": [], "min_value": 1, "max_value": 5, "step": 1, "sampling": "linear"}}, {"class_name": "Choice", "config": {"name": "feature_tnetfilters_0", "default": 0, "conditions": [], "values": [0, 8, 16, 32, 64], "ordered": true}}, {"class_name": "Choice", "config": {"name": "feature_tnetconv_dropout", "default": 0.0, "conditions": [], "values": [0.0, 0.1, 0.2], "ordered": true}}, {"class_name": "Int", "config": {"name": "feature_tnetdense", "default": null, "conditions": [], "min_value": 1, "max_value": 5, "step": 1, "sampling": "linear"}}, {"class_name": "Choice", "config": {"name": "feature_tnetdense_dropout", "default": 0.0, "conditions": [], "values": [0.0, 0.1, 0.2], "ordered": true}}, {"class_name": "Choice", "config": {"name": "decoder", "default": 0, "conditions": [], "values": [0, 8, 16, 32, 64], "ordered": true}}, {"class_name": "Choice", "config": {"name": "input_tnetfilters_1", "default": 0, "conditions": [], "values": [0, 8, 16, 32, 64], "ordered": true}}, {"class_name": "Choice", "config": {"name": "feature_tnetfilters_1", "default": 0, "conditions": [], "values": [0, 8, 16, 32, 64], "ordered": true}}, {"class_name": "Choice", "config": {"name": "feature_tnetfilters_2", "default": 0, "conditions": [], "values": [0, 8, 16, 32, 64], "ordered": true}}, {"class_name": "Choice", "config": {"name": "units1", "default": 0, "conditions": [], "values": [0, 8, 16, 32, 64], "ordered": true}}, {"class_name": "Choice", "config": {"name": "input_tnetfilters_2", "default": 0, "conditions": [], "values": [0, 8, 16, 32, 64], "ordered": true}}, {"class_name": "Choice", "config": {"name": "units2", "default": 0, "conditions": [], "values": [0, 8, 16, 32, 64], "ordered": true}}, {"class_name": "Choice", "config": {"name": "units3", "default": 0, "conditions": [], "values": [0, 8, 16, 32, 64], "ordered": true}}, {"class_name": "Choice", "config": {"name": "input_tnetfilters_3", "default": 0, "conditions": [], "values": [0, 8, 16, 32, 64], "ordered": true}}, {"class_name": "Choice", "config": {"name": "input_tnetfilters_4", "default": 0, "conditions": [], "values": [0, 8, 16, 32, 64], "ordered": true}}, {"class_name": "Choice", "config": {"name": "units4", "default": 0, "conditions": [], "values": [0, 8, 16, 32, 64], "ordered": true}}, {"class_name": "Choice", "config": {"name": "feature_tnetfilters_3", "default": 0, "conditions": [], "values": [0, 8, 16, 32, 64], "ordered": true}}, {"class_name": "Choice", "config": {"name": "feature_tnetfilters_4", "default": 0, "conditions": [], "values": [0, 8, 16, 32, 64], "ordered": true}}], "values": {"lr": 0.001, "input_tnetconv": 1, "input_tnetfilters_0": 32, "input_tnetconv_dropout": 0.1, "input_tnetdense": 1, "units0": 16, "input_tnetdense_dropout": 0.1, "encoder": 8, "feature_tnetconv": 4, "feature_tnetfilters_0": 32, "feature_tnetconv_dropout": 0.0, "feature_tnetdense": 4, "feature_tnetdense_dropout": 0.0, "decoder": 8, "input_tnetfilters_1": 8, "feature_tnetfilters_1": 32, "feature_tnetfilters_2": 0, "units1": 64, "input_tnetfilters_2": 32, "units2": 32, "units3": 16, "input_tnetfilters_3": 16, "input_tnetfilters_4": 16, "units4": 16, "feature_tnetfilters_3": 16, "feature_tnetfilters_4": 8}}, "metrics": {"metrics": {"loss": {"direction": "min", "observations": [{"value": [1.5113813877105713], "step": 134}]}, "accuracy": {"direction": "max", "observations": [{"value": [0.5001654028892517], "step": 134}]}, "width_acc": {"direction": "min", "observations": [{"value": [0.9015132188796997], "step": 134}]}, "val_loss": {"direction": "min", "observations": [{"value": [1.6237568855285645], "step": 134}]}, "val_accuracy": {"direction": "max", "observations": [{"value": [0.4683642089366913], "step": 134}]}, "val_width_acc": {"direction": "min", "observations": [{"value": [0.8780487775802612], "step": 134}]}}}, "score": 0.4683642089366913, "best_step": 134, "status": "COMPLETED", "message": null}